flask_migrate/__init__.py
flask_migrate/templates/flask/alembic.ini.mako
flask_migrate/templates/flask/env.py
flask_migrate/templates/flask/README
flask_migrate/templates/flask/script.py.mako
flask_migrate/templates/flask-multidb/alembic.ini.mako
flask_migrate/templates/flask-multidb/env.py
flask_migrate/templates/flask-multidb/README
flask_migrate/templates/flask-multidb/script.py.mako
Flask_Migrate_tw-1.8.1.dist-info/DESCRIPTION.rst
Flask_Migrate_tw-1.8.1.dist-info/METADATA
Flask_Migrate_tw-1.8.1.dist-info/metadata.json
Flask_Migrate_tw-1.8.1.dist-info/RECORD
Flask_Migrate_tw-1.8.1.dist-info/top_level.txt
Flask_Migrate_tw-1.8.1.dist-info/WHEEL
