Metadata-Version: 2.0
Name: Flask-Migrate-tw
Version: 1.8.1
Summary: A custom version of Flask-Migrate, which depends on  Flask-SQLAlchemy-tw(v3.0)using Alembic
Home-page: http://github.com/miguelgrinberg/flask-migrate/
Author: Yan Wu
Author-email: telooon@gmail.com
License: MIT
Platform: any
Classifier: Environment :: Web Environment
Classifier: Intended Audience :: Developers
Classifier: License :: OSI Approved :: MIT License
Classifier: Operating System :: OS Independent
Classifier: Programming Language :: Python
Classifier: Programming Language :: Python :: 2
Classifier: Programming Language :: Python :: 3
Classifier: Topic :: Internet :: WWW/HTTP :: Dynamic Content
Classifier: Topic :: Software Development :: Libraries :: Python Modules
Requires-Dist: Flask (>=0.9)
Requires-Dist: Flask-SQLAlchemy-tw (>=3.0)
Requires-Dist: alembic (>=0.6)
Requires-Dist: Flask-Script (>=0.6)
